quiz_for_kids/__init__.py
quiz_for_kids/core.py
quiz_for_kids/linear_system/__init__.py
quiz_for_kids/linear_system/integer_equations.py
quiz_for_kids/tex/__init__.py
quiz_for_kids/tex/numpy_array.py
quiz_for_kids-0.1.2.dist-info/LICENSE
quiz_for_kids-0.1.2.dist-info/METADATA
quiz_for_kids-0.1.2.dist-info/WHEEL
quiz_for_kids-0.1.2.dist-info/top_level.txt
quiz_for_kids-0.1.2.dist-info/RECORD
