Metadata-Version: 2.1
Name: quiz-for-kids
Version: 0.1.2
Summary: A fun quiz library for kids
Home-page: https://github.com/trucomanx/quiz-for-kids
Author: Fernando Pujaico Rivera
Author-email: fernando.pujaico.rivera@gmail.com
License: UNKNOWN
Platform: UNKNOWN
Classifier: Programming Language :: Python :: 3
Classifier: License :: OSI Approved :: GNU General Public License v3 (GPLv3)
Classifier: Operating System :: OS Independent
Requires-Python: >=3.6
License-File: LICENSE
Requires-Dist: numpy
